image_prep.py
image_sharpner-1.0.1.dist-info/licenses/LICENSE
image_sharpner-1.0.1.dist-info/METADATA
image_sharpner-1.0.1.dist-info/WHEEL
image_sharpner-1.0.1.dist-info/top_level.txt
image_sharpner-1.0.1.dist-info/RECORD
