Metadata-Version: 2.4
Name: image_sharpner
Version: 1.0.1
Summary: A lightweight adaptive multi-frequency image sharpening library.
Author-email: Md Istiak Tanvir <eruddro@gmail.com>, Asma Akter <asmaul9377@gmail.com>
License: MIT
Project-URL: Homepage, https://github.com/ITR-Ruddro/Lightweight-Image-Sharpening-Method
Keywords: image processing,image enhancement,image sharpening,adaptive sharpening,computer vision,opencv,frequency decomposition
Classifier: Programming Language :: Python
Classifier: Programming Language :: Python :: 3
Classifier: Programming Language :: Python :: 3 :: Only
Classifier: License :: OSI Approved :: MIT License
Classifier: Operating System :: OS Independent
Classifier: Topic :: Scientific/Engineering :: Image Processing
Classifier: Intended Audience :: Developers
Classifier: Intended Audience :: Science/Research
Requires-Python: >=3.7
License-File: LICENSE
Requires-Dist: numpy>=1.19
Requires-Dist: opencv-python>=4.0.0
Dynamic: license-file
